ourotools/__init__.py
ourotools/__main__.py
ourotools/core/BA.py
ourotools/core/MAP.py
ourotools/core/ONT.py
ourotools/core/OT.py
ourotools/core/SAM.py
ourotools/core/SC.py
ourotools/core/SEQ.py
ourotools/core/STR.py
ourotools/core/__init__.py
ourotools/core/alternative_splicing_analysis.py
ourotools/core/biobookshelf.py
ourotools/core/core.py
ourotools-0.2.9.dist-info/LICENSE
ourotools-0.2.9.dist-info/METADATA
ourotools-0.2.9.dist-info/WHEEL
ourotools-0.2.9.dist-info/entry_points.txt
ourotools-0.2.9.dist-info/top_level.txt
ourotools-0.2.9.dist-info/RECORD
