Metadata-Version: 2.1
Name: ourotools
Version: 0.2.9
Summary: A comprehensive toolkit for quality control and analysis of single-cell long-read RNA-seq data
Home-page: https://github.com/ahs2202/ouro-tools
Author: Hyunsu An
Author-email: ahs2202@gm.gist.ac.kr
License: MIT
Requires-Python: >=3.11
License-File: LICENSE
Requires-Dist: bitarray>=2.5.1
Requires-Dist: scipy>=1.9.1
Requires-Dist: tqdm>=4.64.1
Requires-Dist: nest-asyncio>=1.5.6
Requires-Dist: joblib>=1.2.0
Requires-Dist: pandas>=1.5.2
Requires-Dist: intervaltree>=3.1.0
Requires-Dist: matplotlib>=3.5.2
Requires-Dist: plotly>=5.18.0
Requires-Dist: regex>=2.5.135
Requires-Dist: owlready2>=0.46
Requires-Dist: scanpy>=1.10.2
Requires-Dist: h5py>=3.8.0
Requires-Dist: mappy>=2.24
Requires-Dist: pysam>=0.18.0
Requires-Dist: pyBigWig>=0.3.22
